math_utils/__init__.py
math_utils/calculator.py
math_utils/converter.py
math_utils/sentiment_analyzer.py
math_utils_demo_zhishengfei-0.1.0.dist-info/METADATA
math_utils_demo_zhishengfei-0.1.0.dist-info/WHEEL
math_utils_demo_zhishengfei-0.1.0.dist-info/top_level.txt
math_utils_demo_zhishengfei-0.1.0.dist-info/RECORD
