Metadata-Version: 2.4
Name: math-utils-demo-ZHISHENGFEI
Version: 0.1.0
Summary: 简易数学工具库
Author-email: ZHISHENGFEI <735534699@qq.com>
Requires-Python: >=3.8
Requires-Dist: vaderSentiment>=3.3.2
